dlclibrary/__init__.py
dlclibrary/version.py
dlclibrary/dlcmodelzoo/__init__.py
dlclibrary/dlcmodelzoo/modelzoo_download.py
dlclibrary/dlcmodelzoo/modelzoo_urls.yaml
dlclibrary/dlcmodelzoo/modelzoo_urls_pytorch.yaml
dlclibrary/dlcmodelzoo/superanimal_models.json
dlclibrary/dlcmodelzoo/superanimal_configs/superquadruped.yaml
dlclibrary/dlcmodelzoo/superanimal_configs/supertopview.yaml
dlclibrary-0.0.11.data/data/dlclibrary/modelzoo_urls.yaml
dlclibrary-0.0.11.data/data/dlclibrary/modelzoo_urls_pytorch.yaml
dlclibrary-0.0.11.data/data/dlclibrary/superanimal_models.json
dlclibrary-0.0.11.data/data/dlclibrary/superquadruped.yaml
dlclibrary-0.0.11.data/data/dlclibrary/supertopview.yaml
dlclibrary-0.0.11.dist-info/LICENSE
dlclibrary-0.0.11.dist-info/METADATA
dlclibrary-0.0.11.dist-info/NOTICE.yml
dlclibrary-0.0.11.dist-info/WHEEL
dlclibrary-0.0.11.dist-info/top_level.txt
dlclibrary-0.0.11.dist-info/RECORD
