Metadata-Version: 2.1
Name: dlclibrary
Version: 0.0.11
Summary: Lightweight library supporting universal functions for the DeepLabCut ecosystem
Home-page: https://github.com/DeepLabCut/DLClib
Author: A. & M. Mathis Labs
Author-email: alexander@deeplabcut.org
Classifier: Programming Language :: Python :: 3
Classifier: License :: OSI Approved :: GNU Lesser General Public License v3 (LGPLv3)
Classifier: Operating System :: OS Independent
License-File: LICENSE
License-File: NOTICE.yml
Requires-Dist: huggingface-hub
Requires-Dist: ruamel.yaml >=0.15.0
